{
  "entries": [
    {
      "template_id": "carousel_relief_peak_sequence",
      "frame_profile": "4:5_CAROUSEL_SLIDE",
      "slots": [
        "carousel_thesis",
        "closure_contract",
        "slides"
      ]
    },
    {
      "template_id": "carousel_scene_to_principle",
      "frame_profile": "4:5_CAROUSEL_SLIDE",
      "slots": [
        "carousel_thesis",
        "closure_contract",
        "slides"
      ]
    }
  ],
  "registry_id": "registry.template_preview_atlas.carousel_templates.v1",
  "version": "1.0.0"
}
